pdfy/__init__.py
pdfy/pdfy.py
pdfy-1.2.1.dist-info/LICENSE
pdfy-1.2.1.dist-info/METADATA
pdfy-1.2.1.dist-info/NOTICE
pdfy-1.2.1.dist-info/WHEEL
pdfy-1.2.1.dist-info/top_level.txt
pdfy-1.2.1.dist-info/RECORD
