Metadata-Version: 2.1
Name: pdfy
Version: 1.2.1
Summary: A library for converting HTML files into PDF. The tool uses Chrome to render the HTML and print it into a pdf file.
Home-page: https://github.com/mikahama/pdfy
Author: Mika Hämäläinen
Author-email: mika@flyforpoints.com
Classifier: Programming Language :: Python :: 3
Classifier: Programming Language :: Python :: 2
Classifier: Operating System :: OS Independent
License-File: LICENSE
License-File: NOTICE
Requires-Dist: selenium
Requires-Dist: PyChromeDevTools
